setup.py
cielo24/__init__.py
cielo24/actions.py
cielo24/enums.py
cielo24/options.py
cielo24/web_utils.py
cielo24.egg-info/PKG-INFO
cielo24.egg-info/SOURCES.txt
cielo24.egg-info/dependency_links.txt
cielo24.egg-info/requires.txt
cielo24.egg-info/top_level.txt