Metadata-Version: 1.0
Name: cielo24
Version: 1.0.15
Summary: Package for interacting with the cielo24 public REST API
Home-page: http://www.cielo24.com
Author: cielo24
Author-email: support@cielo24.com
License: UNKNOWN
Platform: UNKNOWN
